mynameispooja/__init__.py
mynameispooja/main.py
mynameispooja-0.3.0.dist-info/METADATA
mynameispooja-0.3.0.dist-info/WHEEL
mynameispooja-0.3.0.dist-info/license
mynameispooja-0.3.0.dist-info/top_level.txt
mynameispooja-0.3.0.dist-info/RECORD
