Metadata-Version: 2.1
Name: mynameispooja
Version: 0.3.0
Summary: A simple package for greeting functionality
Home-page: https://github.com/sambhwanipooja
Author: Pooja Sambhwani
Author-email: pooja@example.com
License: UNKNOWN
Platform: UNKNOWN
Classifier: Programming Language :: Python :: 3
Classifier: License :: OSI Approved :: MIT License
Classifier: Operating System :: OS Independent
Requires-Python: >=3.6
